ultralog/__init__.py
ultralog/local.py
ultralog/server.py
ultralog/utils.py
ultralog-0.3.0.dist-info/licenses/LICENSE
ultralog-0.3.0.dist-info/METADATA
ultralog-0.3.0.dist-info/WHEEL
ultralog-0.3.0.dist-info/top_level.txt
ultralog-0.3.0.dist-info/RECORD
