Metadata-Version: 2.4
Name: ultralog
Version: 0.3.0
Summary: High-performance thread-safe logger with optimized file writing and rotation.
Author-email: BirchKwok <birchkwok@gmail.com>
Project-URL: Homepage, https://github.com/birchkwok/ultralog
Classifier: Programming Language :: Python :: 3
Classifier: License :: OSI Approved :: Apache Software License
Classifier: Operating System :: OS Independent
Requires-Python: >=3.9
License-File: LICENSE
Requires-Dist: fastapi>=0.95.0
Requires-Dist: uvicorn>=0.21.0; platform_system != "Windows"
Requires-Dist: waitress>=2.1.2; platform_system == "Windows"
Requires-Dist: asgiref>=3.7.0; platform_system == "Windows"
Requires-Dist: python-multipart>=0.0.6
Requires-Dist: portalocker>=2.7.0
Dynamic: license-file
